test/__init__.py
test/test.py
randomNicknameSeo2-0.0.1.dist-info/METADATA
randomNicknameSeo2-0.0.1.dist-info/WHEEL
randomNicknameSeo2-0.0.1.dist-info/top_level.txt
randomNicknameSeo2-0.0.1.dist-info/RECORD
