Metadata-Version: 2.1
Name: randomNicknameSeo2
Version: 0.0.1
Summary: randomNicknameSeo2
Home-page: https://github.com/plan11plan/randomNicknameSeo2
Download-URL: https://github.com/plan11plan/randomNicknameSeo2
Author: Seo
Classifier: Programming Language :: Python :: 3
